yaset/__init__.py
yaset/yaset.py
yaset/management/__init__.py
yaset/management/commands/__init__.py
yaset/management/commands/create_local.py
yaset/tests/__init__.py
yaset/tests/test_yaset.py
yaset/tests/fixtures/__init__.py
yaset/tests/fixtures/bad_redirect/__init__.py
yaset/tests/fixtures/bad_redirect/local_settings/__init__.py
yaset/tests/fixtures/no_redirect/__init__.py
yaset/tests/fixtures/no_redirect/local_settings/__init__.py
yaset/tests/fixtures/no_secret/__init__.py
yaset/tests/fixtures/no_secret/local_settings/__init__.py
yaset/tests/fixtures/no_secret/local_settings/development.py
yaset/tests/fixtures/no_secret/local_settings/nested.py
yaset/tests/fixtures/working/__init__.py
yaset/tests/fixtures/working/local_settings/__init__.py
yaset/tests/fixtures/working/local_settings/development.py
yaset/tests/fixtures/working/local_settings/nested.py
django_yaset-0.2.0.dist-info/LICENSE
django_yaset-0.2.0.dist-info/METADATA
django_yaset-0.2.0.dist-info/WHEEL
django_yaset-0.2.0.dist-info/top_level.txt
django_yaset-0.2.0.dist-info/RECORD
