Metadata-Version: 2.1
Name: django-yaset
Version: 0.2.0
Summary: Django settings utilities
Home-page: https://github.com/cltrudeau/django-yaset
Author: Christopher Trudeau
Author-email: ctrudeau+pypi@arsensa.com
License: MIT
Keywords: django,state machine
Platform: UNKNOWN
Classifier: Development Status :: 4 - Beta
Classifier: Environment :: Web Environment
Classifier: Intended Audience :: Developers
Classifier: License :: OSI Approved :: MIT License
Classifier: Operating System :: OS Independent
Classifier: Programming Language :: Python :: 3.6
Classifier: Programming Language :: Python :: 3.7
Classifier: Topic :: Software Development :: Libraries :: Application Frameworks
Classifier: Topic :: Software Development :: Libraries :: Python Modules
Requires-Dist: Django (>=2.2)
